apacheconfig/__init__.py
apacheconfig/apacheconfigtool.py
apacheconfig/error.py
apacheconfig/flavors.py
apacheconfig/lexer.py
apacheconfig/loader.py
apacheconfig/parser.py
apacheconfig/reader.py
apacheconfig/wloader.py
apacheconfig-0.3.2.dist-info/LICENSE.rst
apacheconfig-0.3.2.dist-info/METADATA
apacheconfig-0.3.2.dist-info/WHEEL
apacheconfig-0.3.2.dist-info/entry_points.txt
apacheconfig-0.3.2.dist-info/top_level.txt
apacheconfig-0.3.2.dist-info/zip-safe
apacheconfig-0.3.2.dist-info/RECORD
